task3/ram.sv
module ram #(
    parameter   ADDRESS_WIDTH = 10,
                DATA_WIDTH =8
)(
    input logic clk,
    input logic wr_en,
    input logic rd_en,
    input logic [ADDRESS_WIDTH-1:0] wr_addr,
    input logic [ADDRESS_WIDTH-1:0] rd_addr,
    input logic [DATA_WIDTH-1:0] din,
    output logic [DATA_WIDTH-1:0] dout
);

logic [DATA_WIDTH-1:0] ram_array [2**ADDRESS_WIDTH-1:0];

always_ff @(posedge clk) begin
    if (wr_en == 1'b1)
        ram_array[wr_addr] <= din;
    if (rd_en == 1'b1)
        //output is synchronous
        dout <= ram_array [rd_addr];

end
endmodule

task3/counter.sv
module counter #(
    parameter WIDTH = 8
)(
    input logic clk,    // Clock
    input logic rst,    // Reset
    input logic en,
    input logic [WIDTH-1:0] offset,
    output logic [WIDTH-1:0] count1, // Count output
   output logic [WIDTH-1:0] count2  // Count output
);

initial 
    begin
        count1 <= {WIDTH{1'b0}};
        count2 <= {WIDTH{1'b0}};
    end


always_ff @ (posedge clk)

    begin
    count1 <= count1 + 1;
    count2 <= count1 + offset;
    end
endmodule

task3/sigdelay.sv
module sigdelay #(
    parameter   A_WIDTH = 8,
                D_WIDTH = 8
)(
    //interface signals
    input logic clk,
    input logic rst,
    input logic en,
    input logic wr,
    input logic rd,
    input logic [D_WIDTH-1:0] mic_signal,
    input logic [D_WIDTH-1:0] offset,
    input logic count1,
    input logic count2,
    output logic [D_WIDTH-1:0] delayed_signal
    
);

    logic [A_WIDTH-1:0] address1; //interconnect wire
    logic [A_WIDTH-1:0] address2;

counter addrCounter(
    .clk (clk),
    .rst (rst),
    .en(en),
    .offset(offset),
    .count1 (address1),
    .count2 (address2)
);

ram sineRom (
    .clk (clk),
    .wr_en (wr),
    .rd_en (rd),
    .din (mic_signal),
    .wr_addr (address1),
    .rd_addr (address2),
    .dout (delayed_signal)
);
endmodule

task3/sigdelay.vcd
$version Generated by VerilatedVcd $end
$date Sun Nov 26 22:14:01 2023 $end
$timescale 1ps $end

 $scope module TOP $end
  $var wire  1 ' clk $end
  $var wire  1 . count1 $end
  $var wire  1 / count2 $end
  $var wire  8 0 delayed_signal [7:0] $end
  $var wire  1 ) en $end
  $var wire  8 , mic_signal [7:0] $end
  $var wire  8 - offset [7:0] $end
  $var wire  1 + rd $end
  $var wire  1 ( rst $end
  $var wire  1 * wr $end
  $scope module sigdelay $end
   $var wire 32 1 A_WIDTH [31:0] $end
   $var wire 32 1 D_WIDTH [31:0] $end
   $var wire  8 # address1 [7:0] $end
   $var wire  8 $ address2 [7:0] $end
   $var wire  1 ' clk $end
   $var wire  1 . count1 $end
   $var wire  1 / count2 $end
   $var wire  8 0 delayed_signal [7:0] $end
   $var wire  1 ) en $end
   $var wire  8 , mic_signal [7:0] $end
   $var wire  8 - offset [7:0] $end
   $var wire  1 + rd $end
   $var wire  1 ( rst $end
   $var wire  1 * wr $end
   $scope module addrCounter $end
    $var wire 32 1 WIDTH [31:0] $end
    $var wire  1 ' clk $end
    $var wire  8 # count1 [7:0] $end
    $var wire  8 $ count2 [7:0] $end
    $var wire  1 ) en $end
    $var wire  8 - offset [7:0] $end
    $var wire  1 ( rst $end
   $upscope $end
   $scope module sineRom $end
    $var wire 32 2 ADDRESS_WIDTH [31:0] $end
    $var wire 32 1 DATA_WIDTH [31:0] $end
    $var wire  1 ' clk $end
    $var wire  8 , din [7:0] $end
    $var wire  8 0 dout [7:0] $end
    $var wire 10 & rd_addr [9:0] $end
    $var wire  1 + rd_en $end
    $var wire 10 % wr_addr [9:0] $end
    $var wire  1 * wr_en $end
   $upscope $end
  $upscope $end
 $upscope $end
$enddefinitions $end


#0
b00000000 #
b00000000 $
b0000000000 %
b0000000000 &
1'
0(
0)
1*
1+
b00000000 ,
b00000001 -
0.
0/
b00000000 0
b00000000000000000000000000001000 1
b00000000000000000000000000001010 2
#1
0'
#2
b00000001 #
b00000001 $
b0000000001 %
b0000000001 &
1'
b01111001 ,
b00110000 -
#3
0'
#4
b00000010 #
b00110001 $
b0000000010 %
b0000110001 &
1'
b01110111 ,
#5
0'
#6
b00000011 #
b00110010 $
b0000000011 %
b0000110010 &
1'
b01110100 ,
#7
0'
#8
b00000100 #
b00110011 $
b0000000100 %
b0000110011 &
1'
b01110000 ,
#9
0'
#10
b00000101 #
b00110100 $
b0000000101 %
b0000110100 &
1'
b01101011 ,
#11
0'
#12
b00000110 #
b00110101 $
b0000000110 %
b0000110101 &
1'
b01100111 ,
#13
0'
#14
b00000111 #
b00110110 $
b0000000111 %
b0000110110 &
1'
b01100101 ,
#15
0'
#16
b00001000 #
b00110111 $
b0000001000 %
b0000110111 &
1'
b01100000 ,
#17
0'
#18
b00001001 #
b00111000 $
b0000001001 %
b0000111000 &
1'
#19
0'
#20
b00001010 #
b00111001 $
b0000001010 %
b0000111001 &
1'
b01011100 ,
#21
0'
#22
b00001011 #
b00111010 $
b0000001011 %
b0000111010 &
1'
b01010111 ,
#23
0'
#24
b00001100 #
b00111011 $
b0000001100 %
b0000111011 &
1'
b01011001 ,
#25
0'
#26
b00001101 #
b00111100 $
b0000001101 %
b0000111100 &
1'
b01010110 ,
#27
0'
#28
b00001110 #
b00111101 $
b0000001110 %
b0000111101 &
1'
b01011000 ,
#29
0'
#30
b00001111 #
b00111110 $
b0000001111 %
b0000111110 &
1'
b01010111 ,
#31
0'
#32
b00010000 #
b00111111 $
b0000010000 %
b0000111111 &
1'
b01011000 ,
#33
0'
#34
b00010001 #
b01000000 $
b0000010001 %
b0001000000 &
1'
b01010011 ,
#35
0'
#36
b00010010 #
b01000001 $
b0000010010 %
b0001000001 &
1'
b01010001 ,
#37
0'
#38
b00010011 #
b01000010 $
b0000010011 %
b0001000010 &
1'
b01010000 ,
#39
0'
#40
b00010100 #
b01000011 $
b0000010100 %
b0001000011 &
1'
b01010001 ,
#41
0'
#42
b00010101 #
b01000100 $
b0000010101 %
b0001000100 &
1'
b01001111 ,
#43
0'
#44
b00010110 #
b01000101 $
b0000010110 %
b0001000101 &
1'
b01010100 ,
#45
0'
#46
b00010111 #
b01000110 $
b0000010111 %
b0001000110 &
1'
b01011000 ,
#47
0'
#48
b00011000 #
b01000111 $
b0000011000 %
b0001000111 &
1'
b01011001 ,
#49
0'
#50
b00011001 #
b01001000 $
b0000011001 %
b0001001000 &
1'
#51
0'
#52
b00011010 #
b01001001 $
b0000011010 %
b0001001001 &
1'
b01011100 ,
#53
0'
#54
b00011011 #
b01001010 $
b0000011011 %
b0001001010 &
1'
b01011110 ,
#55
0'
#56
b00011100 #
b01001011 $
b0000011100 %
b0001001011 &
1'
#57
0'
#58
b00011101 #
b01001100 $
b0000011101 %
b0001001100 &
1'
#59
0'
#60
b00011110 #
b01001101 $
b0000011110 %
b0001001101 &
1'
b01011111 ,
#61
0'
#62
b00011111 #
b01001110 $
b0000011111 %
b0001001110 &
1'
b01011101 ,
#63
0'
#64
b00100000 #
b01001111 $
b0000100000 %
b0001001111 &
1'
#65
0'
#66
b00100001 #
b01010000 $
b0000100001 %
b0001010000 &
1'
b01011100 ,
#67
0'
#68
b00100010 #
b01010001 $
b0000100010 %
b0001010001 &
1'
b01011101 ,
#69
0'
#70
b00100011 #
b01010010 $
b0000100011 %
b0001010010 &
1'
b01100011 ,
#71
0'
#72
b00100100 #
b01010011 $
b0000100100 %
b0001010011 &
1'
b01100111 ,
#73
0'
#74
b00100101 #
b01010100 $
b0000100101 %
b0001010100 &
1'
b01101001 ,
#75
0'
#76
b00100110 #
b01010101 $
b0000100110 %
b0001010101 &
1'
#77
0'
#78
b00100111 #
b01010110 $
b0000100111 %
b0001010110 &
1'
b01101011 ,
#79
0'
#80
b00101000 #
b01010111 $
b0000101000 %
b0001010111 &
1'
b01101100 ,
#81
0'
#82
b00101001 #
b01011000 $
b0000101001 %
b0001011000 &
1'
#83
0'
#84
b00101010 #
b01011001 $
b0000101010 %
b0001011001 &
1'
b01101111 ,
#85
0'
#86
b00101011 #
b01011010 $
b0000101011 %
b0001011010 &
1'
b01110010 ,
#87
0'
#88
b00101100 #
b01011011 $
b0000101100 %
b0001011011 &
1'
b01110101 ,
#89
0'
#90
b00101101 #
b01011100 $
b0000101101 %
b0001011100 &
1'
b01110110 ,
#91
0'
#92
b00101110 #
b01011101 $
b0000101110 %
b0001011101 &
1'
b01111001 ,
#93
0'
#94
b00101111 #
b01011110 $
b0000101111 %
b0001011110 &
1'
b01110111 ,
#95
0'
#96
b00110000 #
b01011111 $
b0000110000 %
b0001011111 &
1'
b01111100 ,
#97
0'
#98
b00110001 #
b01100000 $
b0000110001 %
b0001100000 &
1'
b01111001 ,
#99
0'
#100
b00110010 #
b01100001 $
b0000110010 %
b0001100001 &
1'
#101
0'
#102
b00110011 #
b01100010 $
b0000110011 %
b0001100010 &
1'
b01110110 ,
#103
0'
#104
b00110100 #
b01100011 $
b0000110100 %
b0001100011 &
1'
b01111010 ,
#105
0'
#106
b00110101 #
b01100100 $
b0000110101 %
b0001100100 &
1'
b01110111 ,
#107
0'
#108
b00110110 #
b01100101 $
b0000110110 %
b0001100101 &
1'
b01111011 ,
#109
0'
#110
b00110111 #
b01100110 $
b0000110111 %
b0001100110 &
1'
#111
0'
#112
b00111000 #
b01100111 $
b0000111000 %
b0001100111 &
1'
#113
0'
#114
b00111001 #
b01101000 $
b0000111001 %
b0001101000 &
1'
b01111010 ,
#115
0'
#116
b00111010 #
b01101001 $
b0000111010 %
b0001101001 &
1'
b01111101 ,
#117
0'
#118
b00111011 #
b01101010 $
b0000111011 %
b0001101010 &
1'
b01111011 ,
#119
0'
#120
b00111100 #
b01101011 $
b0000111100 %
b0001101011 &
1'
#121
0'
#122
b00111101 #
b01101100 $
b0000111101 %
b0001101100 &
1'
b01111001 ,
#123
0'
#124
b00111110 #
b01101101 $
b0000111110 %
b0001101101 &
1'
#125
0'
#126
b00111111 #
b01101110 $
b0000111111 %
b0001101110 &
1'
b01110111 ,
#127
0'
#128
b01000000 #
b01101111 $
b0001000000 %
b0001101111 &
1'
b01110110 ,
#129
0'
#130
b01000001 #
b01110000 $
b0001000001 %
b0001110000 &
1'
b01110011 ,
#131
0'
#132
b01000010 #
b01110001 $
b0001000010 %
b0001110001 &
1'
b01111001 ,
#133
0'
#134
b01000011 #
b01110010 $
b0001000011 %
b0001110010 &
1'
b01110110 ,
#135
0'
#136
b01000100 #
b01110011 $
b0001000100 %
b0001110011 &
1'
#137
0'
#138
b01000101 #
b01110100 $
b0001000101 %
b0001110100 &
1'
b01110001 ,
#139
0'
#140
b01000110 #
b01110101 $
b0001000110 %
b0001110101 &
1'
b01110011 ,
#141
0'
#142
b01000111 #
b01110110 $
b0001000111 %
b0001110110 &
1'
b01101110 ,
#143
0'
#144
b01001000 #
b01110111 $
b0001001000 %
b0001110111 &
1'
b01101011 ,
#145
0'
#146
b01001001 #
b01111000 $
b0001001001 %
b0001111000 &
1'
#147
0'
#148
b01001010 #
b01111001 $
b0001001010 %
b0001111001 &
1'
b01101001 ,
#149
0'
#150
b01001011 #
b01111010 $
b0001001011 %
b0001111010 &
1'
b01101000 ,
#151
0'
#152
b01001100 #
b01111011 $
b0001001100 %
b0001111011 &
1'
b01101001 ,
#153
0'
#154
b01001101 #
b01111100 $
b0001001101 %
b0001111100 &
1'
b01101101 ,
#155
0'
#156
b01001110 #
b01111101 $
b0001001110 %
b0001111101 &
1'
b01101000 ,
#157
0'
#158
b01001111 #
b01111110 $
b0001001111 %
b0001111110 &
1'
#159
0'
#160
b01010000 #
b01111111 $
b0001010000 %
b0001111111 &
1'
b01100011 ,
#161
0'
#162
b01010001 #
b10000000 $
b0001010001 %
b0010000000 &
1'
#163
0'
#164
b01010010 #
b10000001 $
b0001010010 %
b0010000001 &
1'
b01011111 ,
#165
0'
#166
b01010011 #
b10000010 $
b0001010011 %
b0010000010 &
1'
b01011101 ,
#167
0'
#168
b01010100 #
b10000011 $
b0001010100 %
b0010000011 &
1'
b01011100 ,
#169
0'
#170
b01010101 #
b10000100 $
b0001010101 %
b0010000100 &
1'
#171
0'
#172
b01010110 #
b10000101 $
b0001010110 %
b0010000101 &
1'
b01011011 ,
#173
0'
#174
b01010111 #
b10000110 $
b0001010111 %
b0010000110 &
1'
b01011111 ,
#175
0'
#176
b01011000 #
b10000111 $
b0001011000 %
b0010000111 &
1'
b01100010 ,
#177
0'
#178
b01011001 #
b10001000 $
b0001011001 %
b0010001000 &
1'
b01100100 ,
#179
0'
#180
b01011010 #
b10001001 $
b0001011010 %
b0010001001 &
1'
b01100101 ,
#181
0'
#182
b01011011 #
b10001010 $
b0001011011 %
b0010001010 &
1'
b01101000 ,
#183
0'
#184
b01011100 #
b10001011 $
b0001011100 %
b0010001011 &
1'
b01101011 ,
#185
0'
#186
b01011101 #
b10001100 $
b0001011101 %
b0010001100 &
1'
b01101001 ,
#187
0'
#188
b01011110 #
b10001101 $
b0001011110 %
b0010001101 &
1'
#189
0'
#190
b01011111 #
b10001110 $
b0001011111 %
b0010001110 &
1'
b01100111 ,
#191
0'
#192
b01100000 #
b10001111 $
b0001100000 %
b0010001111 &
1'
b01101011 ,
#193
0'
#194
b01100001 #
b10010000 $
b0001100001 %
b0010010000 &
1'
b01101111 ,
#195
0'
#196
b01100010 #
b10010001 $
b0001100010 %
b0010010001 &
1'
b01110001 ,
#197
0'
#198
b01100011 #
b10010010 $
b0001100011 %
b0010010010 &
1'
b01110100 ,
#199
0'
#200
b01100100 #
b10010011 $
b0001100100 %
b0010010011 &
1'
b01111010 ,
#201
0'
#202
b01100101 #
b10010100 $
b0001100101 %
b0010010100 &
1'
#203
0'
#204
b01100110 #
b10010101 $
b0001100110 %
b0010010101 &
1'
b01111111 ,
#205
0'
#206
b01100111 #
b10010110 $
b0001100111 %
b0010010110 &
1'
b01111100 ,
#207
0'
#208
b01101000 #
b10010111 $
b0001101000 %
b0010010111 &
1'
b01111001 ,
#209
0'
#210
b01101001 #
b10011000 $
b0001101001 %
b0010011000 &
1'
b01110001 ,
#211
0'
#212
b01101010 #
b10011001 $
b0001101010 %
b0010011001 &
1'
b01110000 ,
#213
0'
#214
b01101011 #
b10011010 $
b0001101011 %
b0010011010 &
1'
b01110011 ,
#215
0'
#216
b01101100 #
b10011011 $
b0001101100 %
b0010011011 &
1'
b01110101 ,
#217
0'
#218
b01101101 #
b10011100 $
b0001101101 %
b0010011100 &
1'
b01110001 ,
#219
0'
#220
b01101110 #
b10011101 $
b0001101110 %
b0010011101 &
1'
b01110101 ,
#221
0'
#222
b01101111 #
b10011110 $
b0001101111 %
b0010011110 &
1'
#223
0'
#224
b01110000 #
b10011111 $
b0001110000 %
b0010011111 &
1'
b01111000 ,
#225
0'
#226
b01110001 #
b10100000 $
b0001110001 %
b0010100000 &
1'
b01110110 ,
#227
0'
#228
b01110010 #
b10100001 $
b0001110010 %
b0010100001 &
1'
b01111000 ,
#229
0'
#230
b01110011 #
b10100010 $
b0001110011 %
b0010100010 &
1'
b01111011 ,
#231
0'
#232
b01110100 #
b10100011 $
b0001110100 %
b0010100011 &
1'
b01111001 ,
#233
0'
#234
b01110101 #
b10100100 $
b0001110101 %
b0010100100 &
1'
b01111010 ,
#235
0'
#236
b01110110 #
b10100101 $
b0001110110 %
b0010100101 &
1'
b01111001 ,
#237
0'
#238
b01110111 #
b10100110 $
b0001110111 %
b0010100110 &
1'
b01111000 ,
#239
0'
#240
b01111000 #
b10100111 $
b0001111000 %
b0010100111 &
1'
b01111010 ,
#241
0'
#242
b01111001 #
b10101000 $
b0001111001 %
b0010101000 &
1'
b01110110 ,
#243
0'
#244
b01111010 #
b10101001 $
b0001111010 %
b0010101001 &
1'
b01110010 ,
#245
0'
#246
b01111011 #
b10101010 $
b0001111011 %
b0010101010 &
1'
b01110100 ,
#247
0'
#248
b01111100 #
b10101011 $
b0001111100 %
b0010101011 &
1'
#249
0'
#250
b01111101 #
b10101100 $
b0001111101 %
b0010101100 &
1'
b01110011 ,
#251
0'
#252
b01111110 #
b10101101 $
b0001111110 %
b0010101101 &
1'
b01110111 ,
#253
0'
#254
b01111111 #
b10101110 $
b0001111111 %
b0010101110 &
1'
b01111001 ,
#255
0'
#256
b10000000 #
b10101111 $
b0010000000 %
b0010101111 &
1'
b01110101 ,
#257
0'
#258
b10000001 #
b10110000 $
b0010000001 %
b0010110000 &
1'
#259
0'
#260
b10000010 #
b10110001 $
b0010000010 %
b0010110001 &
1'
b01110001 ,
#261
0'
#262
b10000011 #
b10110010 $
b0010000011 %
b0010110010 &
1'
b01101110 ,
#263
0'
#264
b10000100 #
b10110011 $
b0010000100 %
b0010110011 &
1'
b01101011 ,
#265
0'
#266
b10000101 #
b10110100 $
b0010000101 %
b0010110100 &
1'
b01101100 ,
#267
0'
#268
b10000110 #
b10110101 $
b0010000110 %
b0010110101 &
1'
b01101110 ,
#269
0'
#270
b10000111 #
b10110110 $
b0010000111 %
b0010110110 &
1'
#271
0'
#272
b10001000 #
b10110111 $
b0010001000 %
b0010110111 &
1'
b01110010 ,
#273
0'
#274
b10001001 #
b10111000 $
b0010001001 %
b0010111000 &
1'
b01110110 ,
#275
0'
#276
b10001010 #
b10111001 $
b0010001010 %
b0010111001 &
1'
b01110100 ,
#277
0'
#278
b10001011 #
b10111010 $
b0010001011 %
b0010111010 &
1'
b01110101 ,
#279
0'
#280
b10001100 #
b10111011 $
b0010001100 %
b0010111011 &
1'
#281
0'
#282
b10001101 #
b10111100 $
b0010001101 %
b0010111100 &
1'
b01110100 ,
#283
0'
#284
b10001110 #
b10111101 $
b0010001110 %
b0010111101 &
1'
b01110011 ,
#285
0'
#286
b10001111 #
b10111110 $
b0010001111 %
b0010111110 &
1'
b01110100 ,
#287
0'
#288
b10010000 #
b10111111 $
b0010010000 %
b0010111111 &
1'
b01110010 ,
#289
0'
#290
b10010001 #
b11000000 $
b0010010001 %
b0011000000 &
1'
#291
0'
#292
b10010010 #
b11000001 $
b0010010010 %
b0011000001 &
1'
b01110001 ,
#293
0'
#294
b10010011 #
b11000010 $
b0010010011 %
b0011000010 &
1'
#295
0'
#296
b10010100 #
b11000011 $
b0010010100 %
b0011000011 &
1'
b01110011 ,
#297
0'
#298
b10010101 #
b11000100 $
b0010010101 %
b0011000100 &
1'
b01110000 ,
#299
0'
#300
b10010110 #
b11000101 $
b0010010110 %
b0011000101 &
1'
#301
0'
#302
b10010111 #
b11000110 $
b0010010111 %
b0011000110 &
1'
b01101110 ,
#303
0'
#304
b10011000 #
b11000111 $
b0010011000 %
b0011000111 &
1'
#305
0'
#306
b10011001 #
b11001000 $
b0010011001 %
b0011001000 &
1'
b01101101 ,
#307
0'
#308
b10011010 #
b11001001 $
b0010011010 %
b0011001001 &
1'
#309
0'
#310
b10011011 #
b11001010 $
b0010011011 %
b0011001010 &
1'
b01101110 ,
#311
0'
#312
b10011100 #
b11001011 $
b0010011100 %
b0011001011 &
1'
b01101101 ,
#313
0'
#314
b10011101 #
b11001100 $
b0010011101 %
b0011001100 &
1'
b01100111 ,
#315
0'
#316
b10011110 #
b11001101 $
b0010011110 %
b0011001101 &
1'
b01101100 ,
#317
0'
#318
b10011111 #
b11001110 $
b0010011111 %
b0011001110 &
1'
b01101000 ,
#319
0'
#320
b10100000 #
b11001111 $
b0010100000 %
b0011001111 &
1'
b01101001 ,
#321
0'
#322
b10100001 #
b11010000 $
b0010100001 %
b0011010000 &
1'
b01100110 ,
#323
0'
#324
b10100010 #
b11010001 $
b0010100010 %
b0011010001 &
1'
b01100101 ,
#325
0'
#326
b10100011 #
b11010010 $
b0010100011 %
b0011010010 &
1'
#327
0'
#328
b10100100 #
b11010011 $
b0010100100 %
b0011010011 &
1'
b01100110 ,
#329
0'
#330
b10100101 #
b11010100 $
b0010100101 %
b0011010100 &
1'
#331
0'
#332
b10100110 #
b11010101 $
b0010100110 %
b0011010101 &
1'
b01101000 ,
#333
0'
#334
b10100111 #
b11010110 $
b0010100111 %
b0011010110 &
1'
b01100100 ,
#335
0'
#336
b10101000 #
b11010111 $
b0010101000 %
b0011010111 &
1'
b01100110 ,
#337
0'
#338
b10101001 #
b11011000 $
b0010101001 %
b0011011000 &
1'
b01100100 ,
#339
0'
#340
b10101010 #
b11011001 $
b0010101010 %
b0011011001 &
1'
b01100101 ,
#341
0'
#342
b10101011 #
b11011010 $
b0010101011 %
b0011011010 &
1'
b01100011 ,
#343
0'
#344
b10101100 #
b11011011 $
b0010101100 %
b0011011011 &
1'
#345
0'
#346
b10101101 #
b11011100 $
b0010101101 %
b0011011100 &
1'
#347
0'
#348
b10101110 #
b11011101 $
b0010101110 %
b0011011101 &
1'
b01100100 ,
#349
0'
#350
b10101111 #
b11011110 $
b0010101111 %
b0011011110 &
1'
b01100110 ,
#351
0'
#352
b10110000 #
b11011111 $
b0010110000 %
b0011011111 &
1'
b01100101 ,
#353
0'
#354
b10110001 #
b11100000 $
b0010110001 %
b0011100000 &
1'
b01100001 ,
#355
0'
#356
b10110010 #
b11100001 $
b0010110010 %
b0011100001 &
1'
b01100000 ,
#357
0'
#358
b10110011 #
b11100010 $
b0010110011 %
b0011100010 &
1'
#359
0'
#360
b10110100 #
b11100011 $
b0010110100 %
b0011100011 &
1'
b01011111 ,
#361
0'
#362
b10110101 #
b11100100 $
b0010110101 %
b0011100100 &
1'
b01100000 ,
#363
0'
#364
b10110110 #
b11100101 $
b0010110110 %
b0011100101 &
1'
#365
0'
#366
b10110111 #
b11100110 $
b0010110111 %
b0011100110 &
1'
b01100001 ,
#367
0'
#368
b10111000 #
b11100111 $
b0010111000 %
b0011100111 &
1'
#369
0'
#370
b10111001 #
b11101000 $
b0010111001 %
b0011101000 &
1'
b01100011 ,
#371
0'
#372
b10111010 #
b11101001 $
b0010111010 %
b0011101001 &
1'
b01100101 ,
#373
0'
#374
b10111011 #
b11101010 $
b0010111011 %
b0011101010 &
1'
b01101000 ,
#375
0'
#376
b10111100 #
b11101011 $
b0010111100 %
b0011101011 &
1'
b01101100 ,
#377
0'
#378
b10111101 #
b11101100 $
b0010111101 %
b0011101100 &
1'
#379
0'
#380
b10111110 #
b11101101 $
b0010111110 %
b0011101101 &
1'
b01101001 ,
#381
0'
#382
b10111111 #
b11101110 $
b0010111111 %
b0011101110 &
1'
b01100110 ,
#383
0'
#384
b11000000 #
b11101111 $
b0011000000 %
b0011101111 &
1'
b01100111 ,
#385
0'
#386
b11000001 #
b11110000 $
b0011000001 %
b0011110000 &
1'
b01100110 ,
#387
0'
#388
b11000010 #
b11110001 $
b0011000010 %
b0011110001 &
1'
b01101001 ,
#389
0'
#390
b11000011 #
b11110010 $
b0011000011 %
b0011110010 &
1'
b01101010 ,
#391
0'
#392
b11000100 #
b11110011 $
b0011000100 %
b0011110011 &
1'
b01101000 ,
#393
0'
#394
b11000101 #
b11110100 $
b0011000101 %
b0011110100 &
1'
b01101010 ,
#395
0'
#396
b11000110 #
b11110101 $
b0011000110 %
b0011110101 &
1'
b01101100 ,
#397
0'
#398
b11000111 #
b11110110 $
b0011000111 %
b0011110110 &
1'
b01101011 ,
#399
0'
#400
b11001000 #
b11110111 $
b0011001000 %
b0011110111 &
1'
b01101101 ,
#401
0'
#402
b11001001 #
b11111000 $
b0011001001 %
b0011111000 &
1'
b01101110 ,
#403
0'
#404
b11001010 #
b11111001 $
b0011001010 %
b0011111001 &
1'
b01110010 ,
#405
0'
#406
b11001011 #
b11111010 $
b0011001011 %
b0011111010 &
1'
b01111000 ,
#407
0'
#408
b11001100 #
b11111011 $
b0011001100 %
b0011111011 &
1'
b01110111 ,
#409
0'
#410
b11001101 #
b11111100 $
b0011001101 %
b0011111100 &
1'
b10000000 ,
#411
0'
#412
b11001110 #
b11111101 $
b0011001110 %
b0011111101 &
1'
b01111111 ,
#413
0'
#414
b11001111 #
b11111110 $
b0011001111 %
b0011111110 &
1'
b10000000 ,
#415
0'
#416
b11010000 #
b11111111 $
b0011010000 %
b0011111111 &
1'
b10000001 ,
#417
0'
#418
b11010001 #
b00000000 $
b0011010001 %
b0000000000 &
1'
b10000010 ,
#419
0'
#420
b11010010 #
b00000001 $
b0011010010 %
b0000000001 &
1'
#421
0'
#422
b11010011 #
b00000010 $
b0011010011 %
b0000000010 &
1'
b10000001 ,
b01111001 0
#423
0'
#424
b11010100 #
b00000011 $
b0011010100 %
b0000000011 &
1'
b01111110 ,
b01110111 0
#425
0'
#426
b11010101 #
b00000100 $
b0011010101 %
b0000000100 &
1'
b01111100 ,
b01110100 0
#427
0'
#428
b11010110 #
b00000101 $
b0011010110 %
b0000000101 &
1'
b01111010 ,
b01110000 0
#429
0'
#430
b11010111 #
b00000110 $
b0011010111 %
b0000000110 &
1'
b01111001 ,
b01101011 0
#431
0'
#432
b11011000 #
b00000111 $
b0011011000 %
b0000000111 &
1'
b01110111 ,
b01100111 0
#433
0'
#434
b11011001 #
b00001000 $
b0011011001 %
b0000001000 &
1'
b01111011 ,
b01100101 0
#435
0'
#436
b11011010 #
b00001001 $
b0011011010 %
b0000001001 &
1'
b01111000 ,
b01100000 0
#437
0'
#438
b11011011 #
b00001010 $
b0011011011 %
b0000001010 &
1'
#439
0'
#440
b11011100 #
b00001011 $
b0011011100 %
b0000001011 &
1'
b01110111 ,
b01011100 0
#441
0'
#442
b11011101 #
b00001100 $
b0011011101 %
b0000001100 &
1'
b01110010 ,
b01010111 0
#443
0'
#444
b11011110 #
b00001101 $
b0011011110 %
b0000001101 &
1'
b01110011 ,
b01011001 0
#445
0'
#446
b11011111 #
b00001110 $
b0011011111 %
b0000001110 &
1'
b01110000 ,
b01010110 0
#447
0'
#448
b11100000 #
b00001111 $
b0011100000 %
b0000001111 &
1'
b01110011 ,
b01011000 0
#449
0'
#450
b11100001 #
b00010000 $
b0011100001 %
b0000010000 &
1'
b01110010 ,
b01010111 0
#451
0'
#452
b11100010 #
b00010001 $
b0011100010 %
b0000010001 &
1'
b01110000 ,
b01011000 0
#453
0'
#454
b11100011 #
b00010010 $
b0011100011 %
b0000010010 &
1'
b01110100 ,
b01010011 0
#455
0'
#456
b11100100 #
b00010011 $
b0011100100 %
b0000010011 &
1'
b01010001 0
#457
0'
#458
b11100101 #
b00010100 $
b0011100101 %
b0000010100 &
1'
b01110001 ,
b01010000 0
#459
0'
#460
b11100110 #
b00010101 $
b0011100110 %
b0000010101 &
1'
b01110010 ,
b01010001 0
#461
0'
#462
b11100111 #
b00010110 $
b0011100111 %
b0000010110 &
1'
b01110101 ,
b01001111 0
#463
0'
#464
b11101000 #
b00010111 $
b0011101000 %
b0000010111 &
1'
b01010100 0
#465
0'
#466
b11101001 #
b00011000 $
b0011101001 %
b0000011000 &
1'
b01011000 0
#467
0'
#468
b11101010 #
b00011001 $
b0011101010 %
b0000011001 &
1'
b01111001 ,
b01011001 0
#469
0'
#470
b11101011 #
b00011010 $
b0011101011 %
b0000011010 &
1'
b01111100 ,
#471
0'
#472
b11101100 #
b00011011 $
b0011101100 %
b0000011011 &
1'
b01111010 ,
b01011100 0
#473
0'
#474
b11101101 #
b00011100 $
b0011101101 %
b0000011100 &
1'
b01111011 ,
b01011110 0
#475
0'
#476
b11101110 #
b00011101 $
b0011101110 %
b0000011101 &
1'
b01111100 ,
#477
0'
#478
b11101111 #
b00011110 $
b0011101111 %
b0000011110 &
1'
#479
0'
#480
b11110000 #
b00011111 $
b0011110000 %
b0000011111 &
1'
b01111010 ,
b01011111 0
#481
0'
#482
b11110001 #
b00100000 $
b0011110001 %
b0000100000 &
1'
b01110111 ,
b01011101 0
#483
0'
#484
b11110010 #
b00100001 $
b0011110010 %
b0000100001 &
1'
b01111000 ,
#485
0'
#486
b11110011 #
b00100010 $
b0011110011 %
b0000100010 &
1'
b01011100 0
#487
0'
#488
b11110100 #
b00100011 $
b0011110100 %
b0000100011 &
1'
b01110110 ,
b01011101 0
#489
0'
#490
b11110101 #
b00100100 $
b0011110101 %
b0000100100 &
1'
b01110100 ,
b01100011 0
#491
0'
#492
b11110110 #
b00100101 $
b0011110110 %
b0000100101 &
1'
b01110010 ,
b01100111 0
#493
0'
#494
b11110111 #
b00100110 $
b0011110111 %
b0000100110 &
1'
b01110000 ,
b01101001 0
#495
0'
#496
b11111000 #
b00100111 $
b0011111000 %
b0000100111 &
1'
b01101111 ,
#497
0'
#498
b11111001 #
b00101000 $
b0011111001 %
b0000101000 &
1'
b01101001 ,
b01101011 0
#499
0'
#500
b11111010 #
b00101001 $
b0011111010 %
b0000101001 &
1'
b01101000 ,
b01101100 0
#501
0'
#502
b11111011 #
b00101010 $
b0011111011 %
b0000101010 &
1'
b01100110 ,
#503
0'
#504
b11111100 #
b00101011 $
b0011111100 %
b0000101011 &
1'
b01100101 ,
b01101111 0
#505
0'
#506
b11111101 #
b00101100 $
b0011111101 %
b0000101100 &
1'
b01100111 ,
b01110010 0
#507
0'
#508
b11111110 #
b00101101 $
b0011111110 %
b0000101101 &
1'
b01110101 0
#509
0'
#510
b11111111 #
b00101110 $
b0011111111 %
b0000101110 &
1'
b01100010 ,
b01110110 0
#511
0'
#512
b00000000 #
b00101111 $
b0000000000 %
b0000101111 &
1'
b01111001 0
#513
0'
#514
b00000001 #
b00110000 $
b0000000001 %
b0000110000 &
1'
b01011111 ,
b01110111 0
#515
0'
#516
b00000010 #
b00110001 $
b0000000010 %
b0000110001 &
1'
b01100000 ,
b01111100 0
#517
0'
#518
b00000011 #
b00110010 $
b0000000011 %
b0000110010 &
1'
b01100001 ,
b01111001 0
#519
0'
#520
b00000100 #
b00110011 $
b0000000100 %
b0000110011 &
1'
b01100010 ,
#521
0'
#522
b00000101 #
b00110100 $
b0000000101 %
b0000110100 &
1'
b01100000 ,
b01110110 0
#523
0'
#524
b00000110 #
b00110101 $
b0000000110 %
b0000110101 &
1'
b01111010 0
#525
0'
